jaximal/__init__.py
jaximal/core.py
jaximal/io.py
jaximal/py.typed
jaximal-0.1.1.dist-info/METADATA
jaximal-0.1.1.dist-info/WHEEL
jaximal-0.1.1.dist-info/licenses/LICENSE.txt
jaximal-0.1.1.dist-info/RECORD
